{
    "videos":
        [{
            "title": "$456,000 Squid Game In Real Life!", 
            "creator": "MrBeast",
            "viewcount": "213577836", 
            "thumbnail": "https://img.youtube.com/vi/0e3GPea1Tyg/maxresdefault.jpg",
            "url": "https://www.youtube.com/watch?v=0e3GPea1Tyg"   
        },
        {
            "title": "Turning $0.01 Into $1,000 in 24 Hours",
            "creator": "Ryan Trahan",
            "viewcount": "9561675",
            "thumbnail": "https://img.youtube.com/vi/9Cm8D1L1IzQ/maxresdefault.jpg",
            "url": "https://www.youtube.com/watch?v=9Cm8D1L1IzQ"
        },
        {
            "title": "The Fall of Fall Guys",
            "creator": "Pyrocynical",
            "viewcount": "6794293",
            "thumbnail": "https://img.youtube.com/vi/WyPm6p0GnwY/maxresdefault.jpg",
            "url": "https://www.youtube.com/watch?v=WyPm6p0GnwY"
        },
        {
            "title": "The Dark Side Of The Silk Road",
            "creator": "Barely Sociable",
            "viewcount": "8874460",
            "thumbnail": "https://img.youtube.com/vi/GpMP6Nh3FvU/maxresdefault.jpg",
            "url": "https://www.youtube.com/watch?v=GpMP6Nh3FvU"  
        },
        {
            "title": "Bringing my custom mechanical keyboard to school",
            "creator": "Tech review",
            "viewcount": "646162",
            "thumbnail": "https://img.youtube.com/vi/cf6V6VuQhQk/maxresdefault.jpg",
            "url": "https://www.youtube.com/watch?v=cf6V6VuQhQk"  
        },
        {
            "title": "1938 Tube Stock Heritage Ride - Journey 2 - Amersham to Watford Return - 09/09/2018",
            "creator": " carpediemtraveller",
            "viewcount": "1066",
            "thumbnail": "https://img.youtube.com/vi/rZRhWi7Nf2A/maxresdefault.jpg",
            "url": "https://www.youtube.com/watch?v=rZRhWi7Nf2A"  
        },
        {
            "title": "The Most Dangerous Stuff in the Universe - Strange Stars Explained",
            "creator": " Kurzgesagt – In a Nutshell",
            "viewcount": "17551931",
            "thumbnail": "https://img.youtube.com/vi/p_8yK2kmxoo/maxresdefault.jpg",
            "url": "https://www.youtube.com/watch?v=p_8yK2kmxoo"  
        },
        {
            "title": "Atlas, The Next Generation",
            "creator": "Boston Dynamics",
            "viewcount": "39412672",
            "thumbnail": "https://img.youtube.com/vi/rVlhMGQgDkY/maxresdefault.jpg",
            "url": "https://www.youtube.com/watch?v=rVlhMGQgDkY"  
        },
        {
            "title": "Vik Vicious - Loop Tale",
            "creator": "Vik Vicious",
            "viewcount": "750",
            "thumbnail": "https://img.youtube.com/vi/jhXNWlOxfw8/maxresdefault.jpg",
            "url": "https://www.youtube.com/watch?v=jhXNWlOxfw8"  
        },
        {
            "title": "Powfu & KNOWN. - Survivor (Official Music Video)",
            "creator": "KNOWNBOY",
            "viewcount": "172751",
            "thumbnail": "https://img.youtube.com/vi/LdPp6ikd3Qw/sddefault.jpg",
            "url": "https://www.youtube.com/watch?v=LdPp6ikd3Qw"  
        },
        {
            "title": "27 Quick And Easy Crafts To Make At Home",
            "creator": "5-Minute Crafts",
            "viewcount": "10288022",
            "thumbnail": "https://img.youtube.com/vi/lWI1CHKTfF0/maxresdefault.jpg",
            "url": "https://www.youtube.com/watch?v=lWI1CHKTfF0"  
        },
        {
            "title": "J. Cole - MIDDLE CHILD",
            "creator": "J. Cole",
            "viewcount": "216972458",
            "thumbnail": "https://img.youtube.com/vi/WILNIXZr2oc/maxresdefault.jpg",
            "url": "https://www.youtube.com/watch?v=WILNIXZr2oc"  
        },
        {
            "title": "FULL MATCH - Big E vs. Apollo Crews vs. Sami Zayn - Intercontinental Title: SmackDown, Feb. 5, 2021",
            "creator": "WWE",
            "viewcount": "70313",
            "thumbnail": "https://img.youtube.com/vi/ep7jX1uAs9Q/maxresdefault.jpg",
            "url": "https://www.youtube.com/watch?v=ep7jX1uAs9Q"  
        },
        {
            "title": "Billie Eilish - you should see me in a crown (Official Video By Takashi Murakami)",
            "creator": "Billie Eilish",
            "viewcount": "93468947",
            "thumbnail": "https://img.youtube.com/vi/coLerbRvgsQ/maxresdefault.jpg",
            "url": "https://www.youtube.com/watch?v=coLerbRvgsQ"  
        },
        {
            "title": "PRE-SEASON | Moana Pasifika v Chiefs (2022)",
            "creator": "All Blacks",
            "viewcount": "116781",
            "thumbnail": "https://img.youtube.com/vi/VE3N7WLgTUo/maxresdefault.jpg",
            "url": "https://www.youtube.com/watch?v=VE3N7WLgTUo"  
        },
        {
            "title": "Full Boxing Strength session | Max bench",
            "creator": "Eddie 'The Beast' Hall",
            "viewcount": "183687",
            "thumbnail": "https://img.youtube.com/vi/0EytJZFJpgU/maxresdefault.jpg",
            "url": "https://www.youtube.com/watch?v=0EytJZFJpgU"  
        },
        {
            "title": "MOUSE Trailer #2 | Lee Seung Gi, Lee Hee Joon, Kyung Soo Jin | Now on Viu",
            "creator": "Viu Singapore",
            "viewcount": "302268",
            "thumbnail": "https://img.youtube.com/vi/9-0GLwf5JA4/maxresdefault.jpg",
            "url": "https://www.youtube.com/watch?v=9-0GLwf5JA4"  
        },
        {
            "title": "Every angle of Mo Salah's stunning solo goal against Manchester City",
            "creator": "Liverpool FC",
            "viewcount": "2393918",
            "thumbnail": "https://img.youtube.com/vi/iZ68OskGqow/maxresdefault.jpg",
            "url": "https://www.youtube.com/watch?v=iZ68OskGqow"  
        },
        {
            "title": "Anuel AA, Daddy Yankee, Karol G, Ozuna & J Balvin - China (Video Oficial)",
            "creator": "Anuel AA",
            "viewcount": "1827376096",
            "thumbnail": "https://img.youtube.com/vi/0VR3dfZf9Yg/maxresdefault.jpg",
            "url": "https://www.youtube.com/watch?v=0VR3dfZf9Yg"  
        },
        {
            "title": "Ice Cube x Mc Ren x Dr. Dre ⥈ Write This Down; Subtitulado al Español",
            "creator": "Triste realidad",
            "viewcount": "26682740",
            "thumbnail": "https://img.youtube.com/vi/Q3IMJZlqRHE/maxresdefault.jpg",
            "url": "https://www.youtube.com/watch?v=Q3IMJZlqRHE"  
        },
        {
            "title": "Solving Logarithmic Equations",
            "creator": "The Organic Chemistry Tutor",
            "viewcount": "1720361",
            "thumbnail": "https://img.youtube.com/vi/fnhFneOz6n8/maxresdefault.jpg",
            "url": "https://www.youtube.com/watch?v=fnhFneOz6n8"  
        },
        {
            "title": "Chris Brown - Party feat. Usher & Gucci Mane - (Lyrics)",
            "creator": "@Vinimarinho92",
            "viewcount": "24366339",
            "thumbnail": "https://img.youtube.com/vi/u0QlyJ2T1BM/sddefault.jpg",
            "url": "https://www.youtube.com/watch?v=u0QlyJ2T1BM"  
        },
        {
            "title": "Winning Moments | Islamabad United vs Lahore Qalandars | Match 12 | HBL PSL 7 | ML2G",
            "creator": "Sports Central",
            "viewcount": "373311",
            "thumbnail": "https://img.youtube.com/vi/_AeHv6pALiY/maxresdefault.jpg",
            "url": "https://www.youtube.com/watch?v=_AeHv6pALiY"  
        },
        {
            "title": "Destroying Our Little Sister's Phone, Then Giving Her A iPhone 11",
            "creator": "Lucas and Marcus",
            "viewcount": "14254629",
            "thumbnail": "https://img.youtube.com/vi/c0vc6FZTcdU/maxresdefault.jpg",
            "url": "https://www.youtube.com/watch?v=c0vc6FZTcdU"  
        },
        {
            "title": "Raised by Wolves Season 2 Episode 1 & 2 Breakdown | Recap & Review",
            "creator": "Pete Peppers",
            "viewcount": "12568",
            "thumbnail": "https://img.youtube.com/vi/y4eKkxiI7Z8/maxresdefault.jpg",
            "url": "https://www.youtube.com/watch?v=y4eKkxiI7Z8"  
        },
        {
            "title": "Enter - G.O.L (ft. Michael Haze) (prod. Enter) (2021)",
            "creator": "Enter",
            "viewcount": "72500",
            "thumbnail": "https://img.youtube.com/vi/4qHYryNFe00/maxresdefault.jpg",
            "url": "https://www.youtube.com/watch?v=4qHYryNFe00"  
        },
        {
            "title": "NF - LAYERS (Lyrics)",
            "creator": "2H Music",
            "viewcount": "432177",
            "thumbnail": "https://img.youtube.com/vi/3MdUQnUe-Cw/maxresdefault.jpg",
            "url": "https://www.youtube.com/watch?v=3MdUQnUe-Cw"  
        },
        {
            "title": "“Crowd-1” şirkətinin ölkə ərazisindəki mütəşəkkil dəstəsinin üzvləri saxlanılıblar",
            "creator": "İCTİMAİ TV",
            "viewcount": "13894",
            "thumbnail": "https://img.youtube.com/vi/9EGn0xLNR8Q/maxresdefault.jpg",
            "url": "https://www.youtube.com/watch?v=9EGn0xLNR8Q"  
        },
        {
            "title": "The Police - Every Breath You Take (Official Video)",
            "creator": "The Police",
            "viewcount": "923143832",
            "thumbnail": "https://img.youtube.com/vi/OMOGaugKpzs/maxresdefault.jpg",
            "url": "https://www.youtube.com/watch?v=OMOGaugKpzs"  
        },
        {
            "title": "Top 10 best mouse traps / Simple mouse traps with plastic pipes / The mice cannot get out",
            "creator": "mouse channel",
            "viewcount": "16765972",
            "thumbnail": "https://img.youtube.com/vi/We4ReDkBKrQ/maxresdefault.jpg",
            "url": "https://www.youtube.com/watch?v=We4ReDkBKrQ"  
        },
        {
            "title": "💥TWO (2) GRAND JACKPOTS! Dragon Link - Cosmopolitan Las Vegas💥",
            "creator": "Slot Cracker",
            "viewcount": "2458",
            "thumbnail": "https://img.youtube.com/vi/GIyQPCSjMcM/maxresdefault.jpg",
            "url": "https://www.youtube.com/watch?v=GIyQPCSjMcM"  
        },
        {
            "title": "How Corona Virus Affects Your Body? | COVID-19 | The Dr Binocs Show | Peekaboo Kidz",
            "creator": "Peekaboo Kidz",
            "viewcount": "1130879",
            "thumbnail": "https://img.youtube.com/vi/0yp2zbU4fas/maxresdefault.jpg",
            "url": "https://www.youtube.com/watch?v=0yp2zbU4fas"  
        },
        {
            "title": "OneRepublic - Good Life (One Night in Malibu)",
            "creator": "OneRepublic",
            "viewcount": "35860",
            "thumbnail": "https://img.youtube.com/vi/lXPYzs2BgWg/maxresdefault.jpg",
            "url": "https://www.youtube.com/watch?v=lXPYzs2BgWg"  
        },
        {
            "title": "ANA Carry Hard Game vs 30lvl Tinker & MIDONE",
            "creator": "JustWant2PlayAGame",
            "viewcount": "11359",
            "thumbnail": "https://img.youtube.com/vi/u7F6Zn1mjPM/maxresdefault.jpg",
            "url": "https://www.youtube.com/watch?v=u7F6Zn1mjPM"  
        },
        {
            "title": "Making Powerful Armour For War | Minecraft",
            "creator": "GamerFleet",
            "viewcount": "744206",
            "thumbnail": "https://img.youtube.com/vi/YjNUTi6MdU0/maxresdefault.jpg",
            "url": "https://www.youtube.com/watch?v=YjNUTi6MdU0"  
        },
        {
            "title": "Lease Accounting Overview (the new lease rule)",
            "creator": "Edspira",
            "viewcount": "52536",
            "thumbnail": "https://i3.ytimg.com/vi/X1AMT1IhWaM/hqdefault.jpg",
            "url": "https://www.youtube.com/watch?v=X1AMT1IhWaM"  
        },
        {
            "title": "Improve your English: ALL or WHOLE?",
            "creator": "Adam’s English Lessons · engVid",
            "viewcount": "776750",
            "thumbnail": "https://img.youtube.com/vi/hJAXF8YryL4/maxresdefault.jpg",
            "url": "https://www.youtube.com/watch?v=hJAXF8YryL4"  
        },
        {
            "title": "Skillibeng - Sweet (Official Audio)",
            "creator": "Charlie Pro Records",
            "viewcount": "2596530",
            "thumbnail": "https://img.youtube.com/vi/fLOpPkCfn1M/maxresdefault.jpg",
            "url": "https://www.youtube.com/watch?v=fLOpPkCfn1M"  
        },
        {
            "title": "I Opened my own shop - Trailer Shop Simulator Tamil Gameplay - Part 1 -Sharp Tamil Gaming",
            "creator": "Sharp Tamil Gaming 2",
            "viewcount": "6414",
            "thumbnail": "https://img.youtube.com/vi/AhjFwa_rqgc/maxresdefault.jpg",
            "url": "https://www.youtube.com/watch?v=AhjFwa_rqgc"  
        },
        {
            "title": "Demi Lovato - Heart Attack (Official Video)",
            "creator": "Demi Lovato",
            "viewcount": "669534550",
            "thumbnail": "https://img.youtube.com/vi/AByfaYcOm4A/maxresdefault.jpg",
            "url": "https://www.youtube.com/watch?v=AByfaYcOm4A"  
        },
        {
            "title": "LISA - MONEY (Lyrics)",
            "creator": "S Music",
            "viewcount": "3215976",
            "thumbnail": "https://img.youtube.com/vi/-YDm2r4PgY8/maxresdefault.jpg",
            "url": "https://www.youtube.com/watch?v=-YDm2r4PgY8"  
        },
        {
            "title": "ТРЕЙДЫ ПОП ИТ с МАМОЙ 😱 Pop it trade",
            "creator": "ARUKA MIX",
            "viewcount": "215421",
            "thumbnail": "https://img.youtube.com/vi/jYCgueYRJyI/maxresdefault.jpg",
            "url": "https://www.youtube.com/watch?v=jYCgueYRJyI"  
        },
        {
            "title": "Spend 278 Days To Build A Dream Water Park - Full Video",
            "creator": "Mr.Heang Update",
            "viewcount": "2423828",
            "thumbnail": "https://img.youtube.com/vi/0Gsyiq80yLg/maxresdefault.jpg",
            "url": "https://www.youtube.com/watch?v=0Gsyiq80yLg"  
        },
        {
            "title": "Raising Dion Season 2 | Official Trailer | Netflix",
            "creator": "Netflix",
            "viewcount": "2051139",
            "thumbnail": "https://img.youtube.com/vi/CnORv97hCDM/maxresdefault.jpg",
            "url": "https://www.youtube.com/watch?v=CnORv97hCDM"  
        },
        {
            "title": "The prize is too BIG to get out!",
            "creator": "Plush Time Wins",
            "viewcount": "5375914",
            "thumbnail": "https://img.youtube.com/vi/rp6WDXdBWes/maxresdefault.jpg",
            "url": "https://www.youtube.com/watch?v=rp6WDXdBWes"  
        },
        {
            "title": "Spawn Makes Opponent DISCONNECT! - Mortal Kombat 11: \"Spawn\" Gameplay",
            "creator": "Super",
            "viewcount": "52168",
            "thumbnail": "https://img.youtube.com/vi/jmW68Eo7yCg/maxresdefault.jpg",
            "url": "https://www.youtube.com/watch?v=jmW68Eo7yCg"  
        },
        {
            "title": "Beef Steak Restaurant Style | How to Cook Steak Perfectly Every Time | Beef Stake By BaBa Food RRC",
            "creator": "BaBa Food RRC",
            "viewcount": "199198",
            "thumbnail": "https://img.youtube.com/vi/euKWi_C2RPU/maxresdefault.jpg",
            "url": "https://www.youtube.com/watch?v=euKWi_C2RPU"  
        }]
}